Raman2D/__init__.py
Raman2D/main.py
Raman2D/Layout/__init__.py
Raman2D/Layout/create_button.py
Raman2D/Layout/main_window_att.py
Raman2D/Layout/settings.py
Raman2D/Layout/style.py
Raman2D/Layout/utils_button.py
Raman2D/Plot/__init__.py
Raman2D/Plot/frame_attributes.py
Raman2D/Plot/plot_functions.py
Raman2D/Plot/style_plot.py
Raman2D/Plot/utils.py
Raman2D/Processing/__init__.py
Raman2D/Processing/function_common.py
Raman2D/Processing/raman.py
Raman2D/Si_Background/Si_background.py
Raman2D/Si_Background/Smooth.py
Raman2D/Si_Background/__init__.py
Raman2D/Si_Background/raman_si.py
Raman2D/Si_Background/spectrum_to_tuple.py
raman2d-1.0.5.dist-info/licenses/LICENSE
raman2d-1.0.5.dist-info/METADATA
raman2d-1.0.5.dist-info/WHEEL
raman2d-1.0.5.dist-info/entry_points.txt
raman2d-1.0.5.dist-info/top_level.txt
raman2d-1.0.5.dist-info/RECORD
