Metadata-Version: 2.4
Name: Raman2D
Version: 1.0.5
Summary: Package for Raman TMD data processing and visualization
Author-email: Thibaut Meyer <thibaut.meyer3@gmail.com>
License-Expression: GPL-3.0-or-later
Project-URL: Homepage, https://github.com/thi-mey/Raman2D
Keywords: Raman,MoS2,2D
Classifier: Programming Language :: Python :: 3
Classifier: Operating System :: OS Independent
Requires-Python: >=3.9
License-File: LICENSE
Requires-Dist: fitspy
Requires-Dist: matplotlib
Requires-Dist: pandas
Requires-Dist: Pillow
Requires-Dist: PyQt5==5.15.11
Requires-Dist: PyQt5_sip==12.17.0
Dynamic: license-file
